MANIFEST.in
README.rst
setup.py
bionmr_utils/__init__.py
bionmr_utils.egg-info/PKG-INFO
bionmr_utils.egg-info/SOURCES.txt
bionmr_utils.egg-info/dependency_links.txt
bionmr_utils.egg-info/requires.txt
bionmr_utils.egg-info/top_level.txt
bionmr_utils/data/__init__.py
bionmr_utils/data/rename_tables/anames_DNA.csv
bionmr_utils/data/rename_tables/anames_protein.csv
bionmr_utils/data/rename_tables/anames_termini_DNA.csv
bionmr_utils/data/rename_tables/anames_termini_protein.csv
bionmr_utils/data/rename_tables/rnames_DNA.csv
bionmr_utils/data/rename_tables/rnames_protein.csv
bionmr_utils/md/__init__.py
bionmr_utils/md/repair/__init__.py
bionmr_utils/md/repair/charmm_to_amber.py
bionmr_utils/md/repair/rearrange_residues.py
bionmr_utils/md/shortcuts/__init__.py