Metadata-Version: 2.1
Name: bionmr-utils
Version: 0.0.2
Summary: Aggregate package of internal bionmr utils
Home-page: https://github.com/sizmailov/bionmr-utils
Author: Sergei Izmailov
Author-email: sergei.a.izmailov@gmail.com
License: UNKNOWN
Platform: UNKNOWN
Classifier: Programming Language :: Python :: 3
Classifier: Operating System :: POSIX :: Linux
